code_util/__init__.py
code_util/apidoc_generation.py
code_util/buffer.py
code_util/buffer_redis.py
code_util/env.py
code_util/file.py
code_util/log.py
code_util/markdown.py
code_util/num.py
code_util/plot.py
code_util/setup.py
code_util/str_adv.py
code_util/structures.py
ketool/JConfig.py
ketool/__init__.py
ketool/files.py
ketool/hash_util.py
ketool/logs.py
ketool/setup.py
ketool/buffer/__init__.py
ketool/buffer/bufferbase.py
ketool/buffer/local_many.py
ketool/buffer/local_one.py
ketool/buffer/redis.py
ketool/mlsample/LocalSampleSource.py
ketool/mlsample/MemorySampleSource.py
ketool/mlsample/MinioSampleSource.py
ketool/mlsample/NLSampleSource.py
ketool/mlsample/RandomSet.py
ketool/mlsample/SSHSampleSource.py
ketool/mlsample/SampleSet.py
ketool/mlsample/SampleSet_Util.py
ketool/mlsample/__init__.py
ketool/utils/__init__.py
ketool/utils/progressbar.py
ml2_util/MLModel.py
ml2_util/__init__.py
ml2_util/metrics.py
ml2_util/setup.py
ml2_util/mlconfig_components/__init__.py
ml2_util/mlconfig_components/model_save_process.py
ml2_util/mlconfig_components/train_report_process.py
ml2_util/mlmodel_components/__init__.py
ml2_util/mlmodel_components/tf_modelgraph.py
ml2_util/mlmodel_components/tf_modelstorage.py
ml_util/IterationProcess.py
ml_util/IterationProcessModelBase.py
ml_util/MLComponentBase.py
ml_util/MetricsBase.py
ml_util/TrainableProcess.py
ml_util/TrainableProcessModelBase.py
ml_util/__init__.py
ml_util/metrics/__init__.py
ml_util/metrics/accuracy_metrics.py
ml_util/metrics/precision_metrics.py
nlp_util/BertModelBase.py
nlp_util/TFModelBase.py
nlp_util/__init__.py
nlp_util/default_process.py
nlp_util/setup.py
nlp_util/components/BertEmbedding.py
nlp_util/components/Embedding.py
nlp_util/components/SentenceCut.py
nlp_util/components/WordCut.py
nlp_util/components/__init__.py
nlp_util/piplines/__init__.py
nlp_util/piplines/text_generator.py
sample_util/MinioSampleSource.py
sample_util/NLSampleSource.py
sample_util/RandomSet.py
sample_util/SSHSampleSource.py
tketool.pt-0.3.17.dist-info/LICENSE
tketool.pt-0.3.17.dist-info/METADATA
tketool.pt-0.3.17.dist-info/WHEEL
tketool.pt-0.3.17.dist-info/top_level.txt
tketool.pt-0.3.17.dist-info/RECORD
