Metadata-Version: 2.1
Name: tketool.pt
Version: 0.3.17
Summary: Some base methods for developing
Home-page: http://www.example.com/~cschultz/bvote/
Author: Ke
Author-email: jiangke1207@icloud.com
License: UNKNOWN
Platform: UNKNOWN
Classifier: Programming Language :: Python :: 3
Classifier: License :: OSI Approved :: MIT License
Classifier: Operating System :: OS Independent
License-File: LICENSE
Requires-Dist: tketool (==0.3.17)
Requires-Dist: torch
